CHANGELOG.txt
LICENCE.txt
MANIFEST.in
README.md
setup.py
Designer/BackGroundColor.py
Designer/Color.py
Designer/ForeGroundColor.py
Designer/General.py
Designer/HaxName.py
Designer/RandomColor.py
Designer/Values.py
Designer/__init__.py
TerminalDesigner.egg-info/PKG-INFO
TerminalDesigner.egg-info/SOURCES.txt
TerminalDesigner.egg-info/dependency_links.txt
TerminalDesigner.egg-info/top_level.txt