Metadata-Version: 2.1
Name: TerminalDesigner
Version: 0.0.1
Summary: This is a Terminal designer like(Text Processing) ForeGround, BackGround we can change the colors in 3 different ways using this module.
Home-page: https://nagipragalathan.github.io/Personal_website/home.html
Author: NagiPragalathan
Author-email: nagipragalathan@gmail.com
License: MIT
Keywords: Designer,terminal designer,color designer
Platform: UNKNOWN
Classifier: Development Status :: 5 - Production/Stable
Classifier: Intended Audience :: Education
Classifier: Operating System :: Microsoft :: Windows :: Windows 10
Classifier: License :: OSI Approved :: MIT License
Classifier: Programming Language :: Python :: 3
License-File: LICENCE.txt
